{
	"$schema": "../../node_modules/@cyoc/model/schema.json",
	"name": "CYOC View demo",
	"width": 500,
	"background": "#bada55",
	"parts": [
		{
			"name": "Page 1",
			"background": "#d95555",
			"sections": [
				{
					"name": "Welcome",
					"border": {
						"color": "#000000",
						"thickness": 5,
						"rounding": 25
					},
					"rows": []
				},
				{
					"name": "First choice",
					"rows": []
				}
			]
		},
		{
			"name": "Page 2",
			"sections": [
				{
					"name": "A choice",
					"border": {
						"color": "#1ce",
						"thickness": 5,
						"presence": {
							"top": true,
							"bottom": true
						}
					},
					"rows": []
				}
			]
		}
	]
}